notion2pandas/__init__.py
notion2pandas/n2p_read_write.py
notion2pandas/notion2pandas.py
notion2pandas-1.6.3.dist-info/licenses/LICENSE
notion2pandas-1.6.3.dist-info/METADATA
notion2pandas-1.6.3.dist-info/WHEEL
notion2pandas-1.6.3.dist-info/top_level.txt
notion2pandas-1.6.3.dist-info/RECORD
